<?xml version="1.0" encoding="UTF-8" ?>
<!DOCTYPE mapper PUBLIC "-//mybatis.org//DTD Mapper 3.0//EN" "http://mybatis.org/dtd/mybatis-3-mapper.dtd" >
<mapper namespace="system.mapper.LabelMapper" >
  <resultMap id="BaseResultMap" type="system.model.Label" >
    <!--
      WARNING - @mbggenerated
      This element is automatically generated by MyBatis Generator, do not modify.
    -->
    <id column="ID" property="id" jdbcType="VARCHAR" />
    <result column="BL_NAME" property="name" jdbcType="VARCHAR" />
    <result column="BL_CREATE_TIME" property="createTime" jdbcType="TIMESTAMP" />
    <result column="BL_OPERATION_TIME" property="operationTime" jdbcType="TIMESTAMP" />
  </resultMap>
  <sql id="Example_Where_Clause" >
    <!--
      WARNING - @mbggenerated
      This element is automatically generated by MyBatis Generator, do not modify.
    -->
    <where >
      <foreach collection="oredCriteria" item="criteria" separator="or" >
        <if test="criteria.valid" >
          <trim prefix="(" suffix=")" prefixOverrides="and" >
            <foreach collection="criteria.criteria" item="criterion" >
              <choose >
                <when test="criterion.noValue" >
                  and ${criterion.condition}
                </when>
                <when test="criterion.singleValue" >
                  and ${criterion.condition} #{criterion.value}
                </when>
                <when test="criterion.betweenValue" >
                  and ${criterion.condition} #{criterion.value} and #{criterion.secondValue}
                </when>
                <when test="criterion.listValue" >
                  and ${criterion.condition}
                  <foreach collection="criterion.value" item="listItem" open="(" close=")" separator="," >
                    #{listItem}
                  </foreach>
                </when>
              </choose>
            </foreach>
          </trim>
        </if>
      </foreach>
    </where>
  </sql>
  <sql id="Update_By_Example_Where_Clause" >
    <!--
      WARNING - @mbggenerated
      This element is automatically generated by MyBatis Generator, do not modify.
    -->
    <where >
      <foreach collection="example.oredCriteria" item="criteria" separator="or" >
        <if test="criteria.valid" >
          <trim prefix="(" suffix=")" prefixOverrides="and" >
            <foreach collection="criteria.criteria" item="criterion" >
              <choose >
                <when test="criterion.noValue" >
                  and ${criterion.condition}
                </when>
                <when test="criterion.singleValue" >
                  and ${criterion.condition} #{criterion.value}
                </when>
                <when test="criterion.betweenValue" >
                  and ${criterion.condition} #{criterion.value} and #{criterion.secondValue}
                </when>
                <when test="criterion.listValue" >
                  and ${criterion.condition}
                  <foreach collection="criterion.value" item="listItem" open="(" close=")" separator="," >
                    #{listItem}
                  </foreach>
                </when>
              </choose>
            </foreach>
          </trim>
        </if>
      </foreach>
    </where>
  </sql>
  <sql id="Base_Column_List" >
    <!--
      WARNING - @mbggenerated
      This element is automatically generated by MyBatis Generator, do not modify.
    -->
    ID, BL_NAME, BL_CREATE_TIME, BL_OPERATION_TIME
  </sql>
  <select id="selectByExample" resultMap="BaseResultMap" parameterType="system.model.LabelExample" >
    <!--
      WARNING - @mbggenerated
      This element is automatically generated by MyBatis Generator, do not modify.
    -->
    select
    <if test="distinct" >
      distinct
    </if>
    <include refid="Base_Column_List" />
    from blog_label
    <if test="_parameter != null" >
      <include refid="Example_Where_Clause" />
    </if>
    <if test="orderByClause != null" >
      order by ${orderByClause}
    </if>
  </select>
  <select id="selectByPrimaryKey" resultMap="BaseResultMap" parameterType="java.lang.String" >
    <!--
      WARNING - @mbggenerated
      This element is automatically generated by MyBatis Generator, do not modify.
    -->
    select 
    <include refid="Base_Column_List" />
    from blog_label
    where ID = #{id,jdbcType=VARCHAR}
  </select>
  <delete id="deleteByPrimaryKey" parameterType="java.lang.String" >
    <!--
      WARNING - @mbggenerated
      This element is automatically generated by MyBatis Generator, do not modify.
    -->
    delete from blog_label
    where ID = #{id,jdbcType=VARCHAR}
  </delete>
  <delete id="deleteByExample" parameterType="system.model.LabelExample" >
    <!--
      WARNING - @mbggenerated
      This element is automatically generated by MyBatis Generator, do not modify.
    -->
    delete from blog_label
    <if test="_parameter != null" >
      <include refid="Example_Where_Clause" />
    </if>
  </delete>
  <insert id="insert" parameterType="system.model.Label" >
    <!--
      WARNING - @mbggenerated
      This element is automatically generated by MyBatis Generator, do not modify.
    -->
    <selectKey resultType="java.lang.String" keyProperty="id" order="BEFORE" >
      select replace(uuid(), '-', '')
    </selectKey>
    insert into blog_label (ID, BL_NAME, BL_CREATE_TIME, 
      BL_OPERATION_TIME)
    values (#{id,jdbcType=VARCHAR}, #{name,jdbcType=VARCHAR}, #{createTime,jdbcType=TIMESTAMP}, 
      #{operationTime,jdbcType=TIMESTAMP})
  </insert>
  <insert id="insertSelective" parameterType="system.model.Label" >
    <!--
      WARNING - @mbggenerated
      This element is automatically generated by MyBatis Generator, do not modify.
    -->
    <selectKey resultType="java.lang.String" keyProperty="id" order="BEFORE" >
      select replace(uuid(), '-', '')
    </selectKey>
    insert into blog_label
    <trim prefix="(" suffix=")" suffixOverrides="," >
      <if test="id != null" >
        ID,
      </if>
      <if test="name != null" >
        BL_NAME,
      </if>
      <if test="createTime != null" >
        BL_CREATE_TIME,
      </if>
      <if test="operationTime != null" >
        BL_OPERATION_TIME,
      </if>
    </trim>
    <trim prefix="values (" suffix=")" suffixOverrides="," >
      <if test="id != null" >
        #{id,jdbcType=VARCHAR},
      </if>
      <if test="name != null" >
        #{name,jdbcType=VARCHAR},
      </if>
      <if test="createTime != null" >
        #{createTime,jdbcType=TIMESTAMP},
      </if>
      <if test="operationTime != null" >
        #{operationTime,jdbcType=TIMESTAMP},
      </if>
    </trim>
  </insert>
  <select id="countByExample" parameterType="system.model.LabelExample" resultType="java.lang.Integer" >
    <!--
      WARNING - @mbggenerated
      This element is automatically generated by MyBatis Generator, do not modify.
    -->
    select count(*) from blog_label
    <if test="_parameter != null" >
      <include refid="Example_Where_Clause" />
    </if>
  </select>
  <update id="updateByExampleSelective" parameterType="map" >
    <!--
      WARNING - @mbggenerated
      This element is automatically generated by MyBatis Generator, do not modify.
    -->
    update blog_label
    <set >
      <if test="record.id != null" >
        ID = #{record.id,jdbcType=VARCHAR},
      </if>
      <if test="record.name != null" >
        BL_NAME = #{record.name,jdbcType=VARCHAR},
      </if>
      <if test="record.createTime != null" >
        BL_CREATE_TIME = #{record.createTime,jdbcType=TIMESTAMP},
      </if>
      <if test="record.operationTime != null" >
        BL_OPERATION_TIME = #{record.operationTime,jdbcType=TIMESTAMP},
      </if>
    </set>
    <if test="_parameter != null" >
      <include refid="Update_By_Example_Where_Clause" />
    </if>
  </update>
  <update id="updateByExample" parameterType="map" >
    <!--
      WARNING - @mbggenerated
      This element is automatically generated by MyBatis Generator, do not modify.
    -->
    update blog_label
    set ID = #{record.id,jdbcType=VARCHAR},
      BL_NAME = #{record.name,jdbcType=VARCHAR},
      BL_CREATE_TIME = #{record.createTime,jdbcType=TIMESTAMP},
      BL_OPERATION_TIME = #{record.operationTime,jdbcType=TIMESTAMP}
    <if test="_parameter != null" >
      <include refid="Update_By_Example_Where_Clause" />
    </if>
  </update>
  <update id="updateByPrimaryKeySelective" parameterType="system.model.Label" >
    <!--
      WARNING - @mbggenerated
      This element is automatically generated by MyBatis Generator, do not modify.
    -->
    update blog_label
    <set >
      <if test="name != null" >
        BL_NAME = #{name,jdbcType=VARCHAR},
      </if>
      <if test="createTime != null" >
        BL_CREATE_TIME = #{createTime,jdbcType=TIMESTAMP},
      </if>
      <if test="operationTime != null" >
        BL_OPERATION_TIME = #{operationTime,jdbcType=TIMESTAMP},
      </if>
    </set>
    where ID = #{id,jdbcType=VARCHAR}
  </update>
  <update id="updateByPrimaryKey" parameterType="system.model.Label" >
    <!--
      WARNING - @mbggenerated
      This element is automatically generated by MyBatis Generator, do not modify.
    -->
    update blog_label
    set BL_NAME = #{name,jdbcType=VARCHAR},
      BL_CREATE_TIME = #{createTime,jdbcType=TIMESTAMP},
      BL_OPERATION_TIME = #{operationTime,jdbcType=TIMESTAMP}
    where ID = #{id,jdbcType=VARCHAR}
  </update>
</mapper>